snap_bca_api/__init__.py
snap_bca_api/bca.py
snap_bca_api-1.0.0.dist-info/LICENSE
snap_bca_api-1.0.0.dist-info/METADATA
snap_bca_api-1.0.0.dist-info/WHEEL
snap_bca_api-1.0.0.dist-info/top_level.txt
snap_bca_api-1.0.0.dist-info/RECORD
