Metadata-Version: 2.1
Name: snap_bca_api
Version: 1.0.0
Summary: Bank BCA API (SNAP) Python SDK
Author-email: Oji Setyawan <ojiset22@outlook.com>
License: GNU GENERAL PUBLIC LICENSE
Project-URL: Homepage, https://github.com/tentendigital-id/Snap-BCA-API
Project-URL: Issues, https://github.com/tentendigital-id/Snap-BCA-API/issues
Classifier: Programming Language :: Python :: 3
Classifier: License :: OSI Approved :: GNU General Public License v3 (GPLv3)
Classifier: Operating System :: OS Independent
Requires-Python: >=3.8
License-File: LICENSE
Requires-Dist: certifi ==2024.8.30
Requires-Dist: charset-normalizer ==3.4.0
Requires-Dist: idna ==3.10
Requires-Dist: urllib3 ==2.2.3
Requires-Dist: requests ==2.31.0
Requires-Dist: cffi ==1.17.1
Requires-Dist: cryptography ==43.0.3
Requires-Dist: pycparser ==2.22
Requires-Dist: pyOpenSSL ==24.2.1
